cdk_proxy_api_client/__init__.py
cdk_proxy_api_client/client_wrapper.py
cdk_proxy_api_client/common/__init__.py
cdk_proxy_api_client/common/logging.py
cdk_proxy_api_client/errors.py
cdk_proxy_api_client/exceptions.py
cdk_proxy_api_client/interceptors/__init__.py
cdk_proxy_api_client/plugins/__init__.py
cdk_proxy_api_client/proxy_api.py
cdk_proxy_api_client/user_mappings/__init__.py
cdk_proxy_api_client/vclusters/__init__.py
cdk_proxy_api_client-3.0.0.dist-info/LICENSE
cdk_proxy_api_client-3.0.0.dist-info/METADATA
cdk_proxy_api_client-3.0.0.dist-info/WHEEL
cdk_proxy_api_client-3.0.0.dist-info/RECORD
