Metadata-Version: 2.1
Name: cdk-proxy-api-client
Version: 3.0.0
Summary: Conduktor Proxy API Client
License: LICENSE
Keywords: conduktor,kafka,proxy
Author: John "Preston" Mille
Author-email: john@ews-network.net
Requires-Python: >=3.9,<4.0
Classifier: Development Status :: 2 - Pre-Alpha
Classifier: Intended Audience :: Developers
Classifier: Intended Audience :: System Administrators
Classifier: License :: OSI Approved :: Apache Software License
Classifier: License :: Other/Proprietary License
Classifier: Natural Language :: English
Classifier: Programming Language :: Python :: 3
Classifier: Programming Language :: Python :: 3.9
Classifier: Programming Language :: Python :: 3.10
Classifier: Programming Language :: Python :: 3.11
Requires-Dist: pyjwt (>=2.8,<3.0)
Requires-Dist: requests (>=2.31,<3.0)
Project-URL: Bug Tracker, https://github.com/JohnPreston/cdk-proxy-api-client/issues
Project-URL: CLI & Tools, https://github.com/johnpreston/cdk-gw-tools
Project-URL: Source (GitHub), https://github.com/JohnPreston/cdk-proxy-api-client
